{
  "textbook": "三年级上册",
  "units": [
    {
      "unit_number": 1,
      "title": "水",
      "knowledge_points": [
        {
          "name": "水蒸气与蒸发现象",
          "description": "认识水在常温下变成水蒸气的过程，了解其无色无味、存在于空气中的特征。",
          "difficulty": 2,
          "question_types": [
            "填空",
            "判断",
            "选择"
          ]
        },
        {
          "name": "水的沸腾实验与温度计使用",
          "description": "掌握温度计测量水温的规范操作，观察水受热沸腾时的状态变化及恒温100℃的规律。",
          "difficulty": 3,
          "question_types": [
            "操作题",
            "填空",
            "选择"
          ]
        },
        {
          "name": "水结冰与冰融化的体积变化",
          "description": "探究水由液态变为固态（冰）及吸热融化的过程，重点观察体积膨胀现象。",
          "difficulty": 3,
          "question_types": [
            "判断",
            "填空",
            "规律探索"
          ]
        },
        {
          "name": "物质在水中的溶解限度",
          "description": "通过对比实验探究不同物质（如食盐、小苏打）在相同量水中的溶解能力差异。",
          "difficulty": 4,
          "question_types": [
            "应用题",
            "填空",
            "判断"
          ]
        },
        {
          "name": "加快溶解的方法及对比实验",
          "description": "探究搅拌、温度等因素对溶解快慢的影响，掌握对比实验中的变量控制原则。",
          "difficulty": 4,
          "question_types": [
            "操作题",
            "选择",
            "应用题"
          ]
        },
        {
          "name": "混合物的分离技术",
          "description": "利用溶解性、颗粒大小、沸点差异通过过滤或蒸发的方法将食盐与沙或水分离。",
          "difficulty": 3,
          "question_types": [
            "填空",
            "判断",
            "操作题"
          ]
        }
      ]
    },
    {
      "unit_number": 2,
      "title": "空气",
      "knowledge_points": [
        {
          "name": "空气占据空间实验",
          "description": "通过倒扣杯子等实验验证空气占据空间，并了解空气具有流动性。",
          "difficulty": 2,
          "question_types": [
            "操作题",
            "判断",
            "选择"
          ]
        },
        {
          "name": "空气的压缩性与弹性",
          "description": "比较空气与水在压缩实验中的不同表现，理解空气分子间隙大、易压缩且有弹性的特点。",
          "difficulty": 3,
          "question_types": [
            "填空",
            "画图",
            "对比比较"
          ]
        },
        {
          "name": "空气质量的测量",
          "description": "利用天平通过等量代换法（如回形针、绿豆）证明并定量测量空气具有质量。",
          "difficulty": 3,
          "question_types": [
            "应用题",
            "填空",
            "操作题"
          ]
        },
        {
          "name": "热空气上升及风的成因",
          "description": "通过模拟热气球和风的形成实验，理解热空气受热膨胀变轻上升及冷空气补充形成风的原理。",
          "difficulty": 4,
          "question_types": [
            "填空",
            "画图",
            "规律探索"
          ]
        },
        {
          "name": "空气作为物质的典型特征总结",
          "description": "归纳空气的物理属性（无色、无味、透明、可压缩、有质量）及其对生命的作用。",
          "difficulty": 2,
          "question_types": [
            "填空",
            "判断",
            "选择"
          ]
        }
      ]
    },
    {
      "unit_number": 3,
      "title": "天气",
      "knowledge_points": [
        {
          "name": "气温计的读数与测量",
          "description": "认识气温计结构，掌握在通风阴凉处测量气温及零上、零下数值的读写规则。",
          "difficulty": 2,
          "question_types": [
            "操作题",
            "填空",
            "选择"
          ]
        },
        {
          "name": "降水量的测量与降水等级",
          "description": "制作简易雨量器，按毫米单位测量降水量，并根据标准划分降雨等级。",
          "difficulty": 3,
          "question_types": [
            "填空",
            "操作题",
            "排序/比较"
          ]
        },
        {
          "name": "风向与风力的观测",
          "description": "利用风向标和蒲福风力等级表，通过观察地面物体状态判断风的方向和等级。",
          "difficulty": 3,
          "question_types": [
            "连线/匹配",
            "填空",
            "填空"
          ]
        },
        {
          "name": "云量的识别与形态分类",
          "description": "根据云占据天空的比例判断晴、多云、阴，识别堆积状、层状、纤维状云的特征。",
          "difficulty": 2,
          "question_types": [
            "选择",
            "连线/匹配",
            "画图"
          ]
        },
        {
          "name": "天气预报的制作流程",
          "description": "了解从数据收集、数值预报、人工会商到最终发布的天气预报五大标准环节。",
          "difficulty": 2,
          "question_types": [
            "排序/比较",
            "填空",
            "选择"
          ]
        },
        {
          "name": "天气与气候的差异",
          "description": "区分短时间内变化的天气与长期平均状况的气候，了解二十四节气的作用。",
          "difficulty": 4,
          "question_types": [
            "判断",
            "填空",
            "应用题"
          ]
        }
      ]
    }
  ]
}