{
  "bookId": "chinese-g6down",
  "subject": "chinese",
  "textbook": "语文六年级下册",
  "grade": 6,
  "stories": [
    {
      "id": "chinese-g6down-s1",
      "unitNumber": 1,
      "unitTitle": "民风民俗",
      "storyIndex": 1,
      "title": "奶奶的万宝大锅",
      "language": "Chinese",
      "sentences": [
        "腊八节还没到，奶奶就早早在那口黑黢黢的万宝大锅里翻找起食材来。",
        "她常说，熬腊八粥这种民风民俗，最讲究的就是时间的沉淀和用料的厚实。",
        "于是，这篇文章便以寒冬里的腊八前奏为引子，按时间顺序记叙了这场味蕾盛宴。",
        "农历初七傍晚，奶奶将剥了皮的红枣、洗得透亮的莲子和泡发的扁豆依次放入锅中。",
        "夜里，小火慢煨，那一锅稠糊糊的东西逐渐散发出沁人心脾的香气。",
        "到了初八清晨，重头戏终于登场了。",
        "我不动声色地候在炉边，看着那些米粒在乳白色的粥液里翻滚跳动。",
        "作者对熬粥场景进行了详写，而对我们洗漱准备的过程进行了略写，以此突出节日的氛围。",
        "奶奶用勺子搅动着，那腊八粥就像一锅融化的玛瑙，色泽红润且晶莹剔透。",
        "我忍不住用勺子舀起一口，这便是奶奶笔下最生动、最细腻的细节描写。",
        "热气腾腾的雾气里，每一颗谷物都承载着全家人对生活的美好期盼。",
        "奶奶笑称，这锅粥里藏着远方游子的乡愁，也藏着古诗里托物言志的情怀。",
        "吃完腊八粥，一年的年味儿就这样浓墨重彩地拉开了序幕。",
        "我仿佛在这一碗浓粥里，读懂了传统节日的魅力所在。"
      ],
      "vocabulary_used": [
        "民风民俗",
        "按时间顺序记叙",
        "详写",
        "略写",
        "细节描写",
        "托物言志",
        "腊八粥"
      ],
      "questions": [
        {
          "id": 1,
          "type": "true_false",
          "question": "文中奶奶熬腊八粥是从农历初八当天早上才开始准备食材的。",
          "options": [],
          "answer": "错",
          "explanation": "文中提到农历初七傍晚奶奶已经将食材放入锅中，夜里小火慢煨。"
        },
        {
          "id": 2,
          "type": "choice",
          "question": "文中描述腊八粥时，将其比作什么？",
          "options": [
            "融化的玛瑙",
            "璀璨的繁星",
            "洁白的雪花",
            "碧绿的翡翠"
          ],
          "answer": "融化的玛瑙",
          "explanation": "文中明确写到“那腊八粥就像一锅融化的玛瑙”。"
        },
        {
          "id": 3,
          "type": "fill_blank_text",
          "question": "文中为了突出节日氛围，对什么部分进行了“略写”？",
          "options": [],
          "answer": "洗漱准备",
          "explanation": "文中直接提到“对我们洗漱准备的过程进行了略写”。"
        }
      ]
    },
    {
      "id": "chinese-g6down-s2",
      "unitNumber": 1,
      "unitTitle": "民风民俗",
      "storyIndex": 2,
      "title": "鼓楼下的面具舞者",
      "language": "Chinese",
      "sentences": [
        "藏戏的魅力，总是在那激昂的鼓点声中瞬间引爆全场。",
        "我们来到雪域高原，刚好赶上一场别开生面的民间庆典。",
        "这里的表演艺术采取了先总后分的逻辑结构，这让外地游客能瞬间抓住要领。",
        "表演开始前，老艺人总括了藏戏的三个特点：戴着面具演、不用舞台演、一部戏演三五天。",
        "接着，演员们开始分条缕析地展示那一个个历史悠久的神话传说。",
        "为了体现中心思想，编剧对松赞干布娶亲的故事进行了详写，着重表现他的智慧。",
        "哪怕是面具上一个小小的花纹，都是工匠们极其用心的细节描写。",
        "而对于两地联姻路上的琐事，则采用了略写的方法一笔带过。",
        "表演现场，观众们的阵阵喝彩这是最真实的侧面描写，衬托出戏演得极好。",
        "那种奔放的生命力，仿佛是古诗中对土地深沉热爱的托物言志。",
        "我漫步在摊位间，这里充满了浓郁的节日文化气息。",
        "从酥油茶的清香到面具上的斑斓色彩，每一处都是活生生的民风民俗。",
        "当夕阳余晖洒在演员鲜艳的戏服上时，演出仍没到落幕的时候。",
        "时间仿佛在这里慢了下来，让我们在传统艺术中流连忘返。"
      ],
      "vocabulary_used": [
        "先总后分",
        "详写",
        "略写",
        "侧面描写",
        "托物言志",
        "民风民俗",
        "细节描写"
      ],
      "questions": [
        {
          "id": 4,
          "type": "true_false",
          "question": "藏戏表演通常需要专门的高大舞台才能进行。",
          "options": [],
          "answer": "错",
          "explanation": "文中由于描述藏戏特点时提到“不用舞台演”。"
        },
        {
          "id": 5,
          "type": "choice",
          "question": "文中哪一部分内容体现了“侧面描写”？",
          "options": [
            "演员戏服的颜色",
            "观众们的阵阵喝彩",
            "面具上的小小花纹",
            "酥油茶的清香"
          ],
          "answer": "观众们的阵阵喝彩",
          "explanation": "文中明确提到观众的喝彩是最真实的侧面描写，用以衬托表演精彩。"
        },
        {
          "id": 6,
          "type": "fill_blank_text",
          "question": "这篇文章主要通过哪种“逻辑结构”来介绍藏戏的表演艺术？",
          "options": [],
          "answer": "先总后分",
          "explanation": "文中第三句直接指出“这里的表演艺术采取了先总后分的逻辑结构”。"
        }
      ]
    },
    {
      "id": "chinese-g6down-s3",
      "unitNumber": 2,
      "unitTitle": "外国文学名著",
      "storyIndex": 1,
      "title": "译笔下的奇幻森林",
      "language": "Chinese",
      "sentences": [
        "在这个阴雨连绵的周末，六年级一班的林木正在研读《鲁滨逊漂流记》的三个不同译本。",
        "他惊讶地发现，仅仅是一个海浪的描写，在对比翻译中竟然展现出如此截然不同的意境。",
        "有的译本语言华丽得像丝绸，有的则带着浓郁的‘京味儿’口语，透着一股豪爽劲儿。",
        "林木闭上眼，开始在脑海中编写在这片荒原求生的梗概。",
        "故事的第一阶段，也就是开端，他将其命名为‘绝处逢生’。",
        "他开始从多角度评价人物形象，试图理解主角如何在孤独中建立自己的王国。",
        "“鲁滨逊不只是一个幸存者，更是一个内心强大的逻辑学家。”林木在日记中写道。",
        "他记录下人物在困境中的心理变化，从最初的绝望哭泣到后来的坦然面对。",
        "通过研读这些外国文学名著，林木仿佛也经历了一场心灵的远航。",
        "他学会了在面对挫折时，不再只是抱怨，而是寻找解决问题的智慧。",
        "书架上的那本名著梗概，成了他最宝贵的思维导图。",
        "翻译家们的笔触，像微风拂过湖面，荡起层层认知的涟漪。",
        "下课铃响了，林木还没从鲁滨逊的荒岛上‘划船’回来呢。",
        "他深深体会到，语言的丰富性正是阅读最迷人的地方。"
      ],
      "vocabulary_used": [
        "译本",
        "对比翻译",
        "梗概",
        "评价人物形象",
        "心理变化",
        "外国文学名著",
        "京味儿"
      ],
      "questions": [
        {
          "id": 1,
          "type": "true_false",
          "question": "林木在阅读时发现，不同译本对文字的表达效果是完全一样的。",
          "options": [],
          "answer": "错",
          "explanation": "文中提到林木惊讶地发现不同译本展现出截然不同的意境。"
        },
        {
          "id": 2,
          "type": "choice",
          "question": "林木将鲁滨逊荒岛求生故事的第一阶段命名为什么？",
          "options": [
            "心灵远航",
            "绝处逢生",
            "逻辑学家",
            "京味儿口语"
          ],
          "answer": "绝处逢生",
          "explanation": "原文明确提到：故事的第一阶段，也就是开端，他将其命名为‘绝处逢生’。"
        },
        {
          "id": 3,
          "type": "fill_blank_text",
          "question": "林木认为除了幸存者，鲁滨逊还是一个内心强大的什么人？",
          "options": [],
          "answer": "逻辑学家",
          "explanation": "文中引述林木的话中提到“鲁滨逊不只是一个幸存者，更是一个内心强大的逻辑学家”。"
        }
      ]
    },
    {
      "id": "chinese-g6down-s4",
      "unitNumber": 2,
      "unitTitle": "外国文学名著",
      "storyIndex": 2,
      "title": "汤姆·索亚的影子戏",
      "language": "Chinese",
      "sentences": [
        "话剧社要排演《汤姆·索亚历险记》，李明负责编写整部剧的作品梗概。",
        "他将全剧分为‘墓地风云’、‘荒岛远航’、‘洞穴脱险’三个小标题。",
        "在排练室里，导演要求李明必须多角度评价人物形象，不能把汤姆演成一个纯粹的坏孩子。",
        "李明仔细推敲汤姆在面对乔埃威胁时的心理变化，捕捉那份从胆怯到勇敢的飞跃。",
        "“我们要展现出他在困境中的智慧，而非简单的顽劣。”李明对演员们说。",
        "演员们通过对不同国家戏剧本的对比翻译法，寻找最地道的台词感觉。",
        "他们发现有些外国文学名著的幽默感是藏在文字背后的，需要静心揣摩。",
        "李明在笔记本上画出了汤姆性格的坐标轴，左边是顽皮，右边是正义。",
        "为了体现语言特色，他们特意加入了几句带有家乡风情的生动口语。",
        "排练现场因情节脉络的清晰而变得井然有序。",
        "每一个细节的调整，都是对原著精神的一次深度补白。",
        "汤姆的形象在灯光下逐渐变得立体，仿佛从书页中走了出来。",
        "这部剧最终大获成功，观众们纷纷感叹小英雄的机智。",
        "李明合上厚厚的原著，明白阅读名著不仅仅是为了看故事，更是为了理解人性。"
      ],
      "vocabulary_used": [
        "作品梗概",
        "小标题",
        "评价人物形象",
        "心理变化",
        "对比翻译法",
        "情节脉络",
        "叙事结构"
      ],
      "questions": [
        {
          "id": 1,
          "type": "true_false",
          "question": "李明认为汤姆·索亚仅仅是一个单纯的顽劣少年。",
          "options": [],
          "answer": "错",
          "explanation": "李明要求演员展现出汤姆在困境中的智慧和性格中的正义感，不能演成纯粹的坏孩子。"
        },
        {
          "id": 2,
          "type": "choice",
          "question": "李明通过什么方式来寻找最地道的台词感觉？",
          "options": [
            "大声朗读课文",
            "增加背景音乐",
            "对比翻译法",
            "修改结尾情节"
          ],
          "answer": "对比翻译法",
          "explanation": "文中提到：演员们通过对不同国家戏剧本的对比翻译法，寻找最地道的台词感觉。"
        },
        {
          "id": 3,
          "type": "fill_blank_text",
          "question": "李明为《汤姆·索亚历险记》编写了什么来梳理剧目框架？",
          "options": [],
          "answer": "作品梗概",
          "explanation": "故事第一句话提到了李明负责编写整部剧的作品梗概。"
        }
      ]
    },
    {
      "id": "chinese-g6down-s5",
      "unitNumber": 3,
      "unitTitle": "让真情在笔尖流露",
      "storyIndex": 1,
      "title": "奶奶的老蒲扇",
      "language": "Chinese",
      "sentences": [
        "在这个闷热的午后，时间仿佛不再匆匆，而是被拉得极长极长。",
        "我已经很久没有回到这间旧屋了，空气中弥漫着一股陈旧而温暖的木头香气。",
        "阳光透过窗棂，细碎地洒在斑驳的墙面上，像是一枚枚跳动的金色音符。",
        "奶奶坐在那把咯吱响的藤椅上，手里执着那把边缘已经起毛的老蒲扇。",
        "蒲扇轻轻摇动，带起阵阵凉爽的风，也吹散了夏日的急躁。",
        "我想起小时候，也是在这个位置，阳光照得我昏昏欲睡。",
        "那时候，我觉得蝉鸣是这个世界上最动听的催眠曲，因为有奶奶在身边。",
        "奶奶的动作很慢，一下，两下，每一扇里都藏着揉碎了的疼爱。",
        "我不由自主地走过去，蹲在地砖上，将头轻轻靠在她的膝盖上。",
        "她那双布满老茧的手温柔地抚过我的头发，像是在抚摸一件珍视多年的宝贝。",
        "“燕子飞走了，总有归巢的时候。”奶奶的声音沙哑却透着一股平静的力量。",
        "我的眼眶微微发热，那些在城市里积攒的委屈仿佛瞬间消融在这一摇一摆的风中。",
        "窗外的老枣树似乎也感应到了我的心境，树叶在微风中欢快地相互拍打着。",
        "这哪里只是风，分明是奶奶那颗从未变过的、滚烫的慈爱之心。",
        "我接过那把扇子，学着她的样子，缓缓地为她摇动起这一季的安宁。"
      ],
      "vocabulary_used": [
        "匆匆",
        "融情于事",
        "融情于景",
        "心境",
        "排比",
        "间接抒情"
      ],
      "questions": [
        {
          "id": 1,
          "type": "true_false",
          "question": "文中通过描写老枣树树叶欢快拍打，是为了反衬作者内心的悲伤。",
          "options": [],
          "answer": "错",
          "explanation": "文中作者感受到的是温暖与安宁，老枣树的描写属于随心境而变的景物描写，反映了作者心情的释怀与喜悦。"
        },
        {
          "id": 2,
          "type": "choice",
          "question": "“每一扇里都藏着揉碎了的疼爱”这句话体现了哪种情感表达方式？",
          "options": [
            "直接抒发对奶奶的赞美",
            "通过细节动作融情于事",
            "单纯描写蒲扇的质量好",
            "对古代生活的向往"
          ],
          "answer": "通过细节动作融情于事",
          "explanation": "将抽象的“疼爱”融入奶奶扇扇子这一具体的动作细节中，是本单元“让真情在笔尖流露”的核心技巧。"
        },
        {
          "id": 3,
          "type": "fill_blank_text",
          "question": "作者在城市积攒的什么，在奶奶的扇风中消融了？",
          "options": [],
          "answer": "委屈",
          "explanation": "原文中提到“那些在城市里积攒的委屈仿佛瞬间消融”。"
        }
      ]
    },
    {
      "id": "chinese-g6down-s6",
      "unitNumber": 3,
      "unitTitle": "让真情在笔尖流露",
      "storyIndex": 2,
      "title": "落选后的雨天",
      "language": "Chinese",
      "sentences": [
        "校运动会的名单公布了，在男子立定跳远的那一栏里，没有出现我的名字。",
        "我无力地走出教学楼，只觉得自己像是一只泄了气的皮球。",
        "天空不知何时已经阴沉了下来，厚重的乌云仿佛要直接压到我的头顶上。",
        "那曾经清脆悦耳的小鸟叫声，此刻听起来却像是在肆无忌惮地嘲笑我的失败。",
        "路边的月季花垂下头去，花瓣上沾满了灰尘，看起来狼狈不堪。",
        "我不禁自责地想：为什么明明努力了这么久，结果却依然是一场空？",
        "细雨开始飘落，像是密密麻麻的针，扎得我心底生疼。",
        "我走进雨中，任凭水滴打湿我的衣襟，却不想撑开手中的那把红伞。",
        "突然，我想起体育老师曾说过，每一次跃起前的深蹲，都是为了积攒爆发的力量。",
        "燕子去了，有再来的时候；杨柳枯了，有再青的时候。",
        "虽然这次落选了，但我练习时的汗水难道真的白流了吗？",
        "我抬起头，看见几棵小草在雨水的冲刷下，反而显得更加翠绿挺拔。",
        "那抹绿色逐渐在我的视野里扩大，我的心境也悄然发生了一些变化。",
        "原本阴沉的天空，在我的眼中似乎变成了一幅极具张力的动态水墨画。",
        "我重重地吐出一口气，大步流星地朝家走去，明天也要准时开始晨跑。"
      ],
      "vocabulary_used": [
        "环境描写",
        "心境",
        "《匆匆》句式",
        "反复",
        "融情于景",
        "对比"
      ],
      "questions": [
        {
          "id": 4,
          "type": "choice",
          "question": "故事中作者对天空的感受从“厚重”变为“动态水墨画”，说明了什么？",
          "options": [
            "天气真的变好了",
            "作者的视力恢复了",
            "心境变化影响了感知的景物",
            "他决定去学画画"
          ],
          "answer": "心境变化影响了感知的景物",
          "explanation": "同一环境在不同心境下会呈现出不同的感官特征，这符合本单元环境描写随心情变化的知识点。"
        },
        {
          "id": 5,
          "type": "true_false",
          "question": "“燕子去了，有再来的时候”是引用了朱自清《匆匆》里的名句。",
          "options": [],
          "answer": "对",
          "explanation": "这是《匆匆》开篇的经典排比句式，用于表达时光流逝或事物循环。"
        },
        {
          "id": 6,
          "type": "fill_blank_text",
          "question": "作者在感到失败时，觉得自己像一只什么？",
          "options": [],
          "answer": "泄了气的皮球",
          "explanation": "原文中运用比喻拟人等手法，将自己比作“泄了气的皮球”来形容失落感。"
        }
      ]
    },
    {
      "id": "chinese-g6down-s7",
      "unitNumber": 4,
      "unitTitle": "人物品质",
      "storyIndex": 1,
      "title": "废墟下的石灰吟",
      "language": "Chinese",
      "sentences": [
        "地震过后的废墟旁，年迈的林老师正费力地扒开瓦砾，寻找被掩埋的教案。",
        "夕阳将他的影子拉得很长，原本整洁的西装已满是尘污，显得有些狼狈。",
        "路过的年轻人劝他先去休息，林老师却只是紧抿双唇，眼神里透着一股不容置疑的倔强。",
        "他常说，做人要像他家乡的石灰一样，即便身体破碎，也要留下清白在人间。",
        "这种‘托物言志’的教诲，在这一刻不再是课本上的文字，而成了他此刻真实的写照。",
        "他的手被磨出了血，神态却依然镇定自若，仿佛在完成一件极其神圣的使命。",
        "这让我想起了课文里的品质，那种在危难时刻展现出的坚定信念。",
        "终于，他从缝隙中掏出了那叠泛黄的思想品德教案，脸上露出了欣慰的笑容。",
        "周围的人围拢过来，被老教授这种纯粹的职业操守所震撼。",
        "他说：‘知识的火种不能灭，哪怕只剩一页纸，我也要把它传下去。’",
        "他的言行深深打动了在场的每一个人，大家纷纷加入到清理的行列中。",
        "在这个瓦砾遍地的黄昏，林老师用行动诠释了什么叫高尚的节操。",
        "没有豪言壮语，只有那微微颤抖却极其有力的双手。",
        "就像石灰入火，千锤万凿，只为那份初心不改。",
        "这就是一个平凡师者的‘石灰吟’。"
      ],
      "vocabulary_used": [
        "石灰吟",
        "托物言志",
        "神态",
        "言行",
        "高尚节操",
        "坚定信念"
      ],
      "questions": [
        {
          "id": 1,
          "type": "true_false",
          "question": "文中提到的“石灰吟”不仅仅是一首诗，更象征了林老师的高尚品质。",
          "options": [],
          "answer": "对",
          "explanation": "文中提到林老师用行动诠释了这种精神，将诗句与人物品质结合。"
        },
        {
          "id": 2,
          "type": "choice",
          "question": "文中哪句话最能体现林老师在危难时刻的神态特点？",
          "options": [
            "原本整洁的西装已满是尘污",
            "眼神里透着一股不容置疑的倔强",
            "夕阳将他的影子拉得很长",
            "大家纷纷加入到清理的行列中"
          ],
          "answer": "眼神里透着一股不容置疑的倔强",
          "explanation": "神态描写主要集中在面部表情和眼神，“倔强”准确刻画了其神情。"
        },
        {
          "id": 3,
          "type": "fill_blank_text",
          "question": "林老师通过挖掘教案的行为，用行动诠释了诗人借具体事物表达的什么？",
          "options": [],
          "answer": "高尚节操",
          "explanation": "对应文中第十二句话“诠释了什么叫高尚的节操”。"
        }
      ]
    },
    {
      "id": "chinese-g6down-s8",
      "unitNumber": 4,
      "unitTitle": "人物品质",
      "storyIndex": 2,
      "title": "老街上的辩论赛",
      "language": "Chinese",
      "sentences": [
        "老街的修缮会议上，关于是否要拆掉旧图书馆，大家争论不休。",
        "年轻的建筑师小王站起来发表了演说，他的论证逻辑极其严密。",
        "他首先提出了中心观点：保护旧建筑就是保护城市的根脉。",
        "接着，他展开了论证，引用了《为人民服务》中的奉献精神来强调集体的社会责任。",
        "他采用因果论证的方法，详细说明了拆除老建筑会带来的文化缺失。",
        "小王的外貌看起来很斯文，但此刻他慷慨陈词，眼中闪烁着睿智的光芒。",
        "他的每一句言行都体现了对传统的尊重，这种精神令人肃然起敬。",
        "尽管对方不断质疑，他始终保持着温和而坚定的神态。",
        "‘我们若想更好地为人民服务，就得留住这个社区的历史记忆。’他说。",
        "这种引用论证不仅增强了说服力，更拔高了辩论的立意。",
        "台下的居民代表们听得频频点头，之前反对的意见渐渐微弱了。",
        "最终，会议决定绕过旧图书馆进行街区升级。",
        "这场博弈展示了逻辑的力量，也展现了一个青年对公益事业的坚定信念。",
        "优秀的议论文结构被他巧妙地运用在现实生活的问题解决中。",
        "老街的晚风吹过，历史与现代在这一刻达成了和解。"
      ],
      "vocabulary_used": [
        "中心观点",
        "为人民服务",
        "引用论证",
        "因果论证",
        "逻辑",
        "坚定信念"
      ],
      "questions": [
        {
          "id": 1,
          "type": "choice",
          "question": "小王在论证如何保护老街时，主要采用了哪种论证方法？",
          "options": [
            "比喻论证",
            "对比论证",
            "因果论证",
            "列数字论证"
          ],
          "answer": "因果论证",
          "explanation": "文中明确提到“他采用因果论证的方法，详细说明了拆除老建筑会带来的文化缺失”。"
        },
        {
          "id": 2,
          "type": "true_false",
          "question": "小王在演讲中引用了《为人民服务》中的精神来增强说服力。",
          "options": [],
          "answer": "对",
          "explanation": "文中第四句和第九句描述了小王对《为人民服务》精神的引用。"
        },
        {
          "id": 3,
          "type": "fill_blank_text",
          "question": "小王认为保护旧建筑就是保护城市的什么？",
          "options": [],
          "answer": "根脉",
          "explanation": "文中第三句明确“保护旧建筑就是保护城市的根脉”。"
        }
      ]
    },
    {
      "id": "chinese-g6down-s9",
      "unitNumber": 5,
      "unitTitle": "科学精神",
      "storyIndex": 1,
      "title": "林教授的“旋转”实验室",
      "language": "Chinese",
      "sentences": [
        "科学课上，林教授在黑板上写下了“真理诞生于一百个问号之后”这句话，原本懒散的教室瞬间安静了。",
        "他并没有直接讲课，而是拿出一个特制的实验托盘，上面装满了正在旋转的水流。",
        "“见微知著是一种重要的能力。”林教授指着水流中心形成的细小漩涡，眼神中透着严肃。",
        "小明好奇地举手提问：“教授，为什么不同维度的漩涡旋转方向会不一样呢？”",
        "针对这个疑问，林教授讲起了科学家谢皮罗通过洗澡水的漩涡方向推导地球自转影响的具体事例。",
        "大家开始分组实验，试图用司空见惯的现象去验证那些伟大的结论。",
        "有些同学在不断敲击托盘，想观察震动对旋转的影响，这种打破砂锅问到底的精神让教授很欣慰。",
        "“你们不需要盲从权威，”教授微笑着说，“科学的本质就是不断追问和严谨求证。”",
        "小明在笔记上认真记录着每一次水滴飞溅的方向，他认为这些数据都不容忽视。",
        "他想起《两小儿辩日》里那个面对孔子也敢坚持己见的孩子，明白真理不会因为身份而改变。",
        "经过半个多小时的观察，他们发现水流的旋转趋势在强力外干预下依然遵循着某种惯性。",
        "这种锲而不舍的观测，让原本枯燥的数据变成了通往真相的阶梯。",
        "下课铃响了，但同学们并没有急着离开，依然围着实验台进行辩论。",
        "林教授合上教案，他知道，这颗科学的种子已经在孩子们心中扎下了根。"
      ],
      "vocabulary_used": [
        "真理诞生于一百个问号之后",
        "见微知著",
        "具体事例",
        "两小儿辩日",
        "追问",
        "打破砂锅问到底",
        "锲而不舍",
        "司空见惯"
      ],
      "questions": [
        {
          "id": 1,
          "type": "true_false",
          "question": "小明认为在实验过程中，即使是细微的数据也是不容忽视的。",
          "options": [],
          "answer": "对",
          "explanation": "文中提到“小明在笔记上认真记录着每一次水滴飞溅的方向，他认为这些数据都不容忽视”。"
        },
        {
          "id": 2,
          "type": "choice",
          "question": "故事中林教授举了关于“谢皮罗教授”的例子，是为了说明哪种方法？",
          "options": [
            "通过具体事例说明观点",
            "通过科幻想象构建世界观",
            "通过文言文翻译理解实词",
            "通过体育锻炼增强体质"
          ],
          "answer": "通过具体事例说明观点",
          "explanation": "文中明确提到林教授讲起谢皮罗的具体事例，是为了支撑科学观点。"
        },
        {
          "id": 3,
          "type": "fill_blank_text",
          "question": "文中形容同学们对实验现象有着强烈的好奇心，使用了哪一个四字成语？",
          "options": [],
          "answer": "见微知著",
          "explanation": "文中林教授指着漩涡时提到了“见微知著是一种重要的能力”。"
        }
      ]
    },
    {
      "id": "chinese-g6down-s10",
      "unitNumber": 5,
      "unitTitle": "科学精神",
      "storyIndex": 2,
      "title": "2077年的“学弈”舱",
      "language": "Chinese",
      "sentences": [
        "在2077年的少年宫，一种名为“全息意念学弈”的科幻训练模拟器广受欢迎。",
        "小元进入了模拟舱，他的对手是来自古代的“弈秋”，一位传说中的围棋宗师。",
        "模拟器还原了《学弈》中的经典场景，但增加了一项变量：天空中不时飞过机械大雁。",
        "小元深知“一心以为有鸿鹄将至”是学不好的，于是他强迫自己屏息凝神，目不斜视。",
        "然而，原本专心致志的他发现，那些机械大雁的飞行轨迹竟然蕴含着某种复杂的物理公式。",
        "“如果不弄清楚这种现象，科学探索就停滞了。”小元心里做着激烈的思想斗争。",
        "他想起书本里提到的科学精神，不仅要专心学习，更要对未知的规律保持敏锐觉察。",
        "他冒险改变了下棋的思路，试图通过棋盘上的黑白子推算大雁的动力源规律。",
        "弈秋此时停下了手中的棋子，原本严厉的表情化作了一抹赞许的微笑。",
        "原来，这个关卡考核的不仅是棋艺，更是这种在惯常逻辑中寻找新科学发现的能力。",
        "小元意识到，当“学弈”与“科研”结合时，他的思维空间变得无比广阔。",
        "他不再只是机械地模仿古人的棋谱，而是开始尝试构建属于自己的科幻逻辑逻辑模型。",
        "这种基于科学事实的合理想象，让他最终在这场全息对决中找到了能量守恒的平衡点。",
        "离开模拟舱时，小元感叹：原来最深奥的真理，往往隐藏在最平常的练习中。"
      ],
      "vocabulary_used": [
        "学弈",
        "弈秋",
        "鸿鹄",
        "专心致志",
        "科学精神",
        "科幻想象",
        "逻辑",
        "真理"
      ],
      "questions": [
        {
          "id": 1,
          "type": "true_false",
          "question": "小元在学弈过程中完全没有受到机械大雁的影响，一直只关注棋局本身。",
          "options": [],
          "answer": "错",
          "explanation": "文中提到小元发现了大雁飞行轨迹蕴含物理公式，并尝试推算其动力源规律，并非只关注棋局。"
        },
        {
          "id": 2,
          "type": "choice",
          "question": "“一心以为有鸿鹄将至”这句话在文中形容的是什么状态？",
          "options": [
            "学习时三心二意",
            "对真理锲而不舍",
            "观察敏锐的科研态度",
            "棋艺高超的境界"
          ],
          "answer": "学习时三心二意",
          "explanation": "在《学弈》原文和本文语境中，这都指代心思不在学习内容本身（三心二意）。"
        },
        {
          "id": 3,
          "type": "fill_blank_text",
          "question": "小元不仅关注棋局，还尝试构建属于自己的什么模型？",
          "options": [],
          "answer": "逻辑模型",
          "explanation": "文中倒数第三句提到“而是开始尝试构建属于自己的科幻逻辑逻辑模型”。"
        }
      ]
    },
    {
      "id": "chinese-g6down-s11",
      "unitNumber": 6,
      "unitTitle": "难忘小学生活",
      "storyIndex": 1,
      "title": "时空胶囊的秘密",
      "language": "Chinese",
      "sentences": [
        "在这个充满离别气息的夏天，六年级一班的同学们决定最后聚在一起，发起一场名为“时光守护者”的特别活动。",
        "班长林悦拿出一份详尽的活动策划书，上面清晰地标注着分工明细：有的负责摄影，有的负责采购。",
        "大家准备制作一本独一无二的成长纪念册，以此留住那些闪闪发光的童年碎片。",
        "林悦在黑板上画出了一条长长的时间轴，带领大家开始搜集成长素材。",
        "“你们还记得二年级时，由于突降暴雨，老师背着我们过积水坑的事吗？”林悦轻声问道。",
        "大家纷纷打开了记忆的闸门，将那些泛黄的照片、写满红叉的卷子和操场上的笑声作为素材进行分类整理。",
        "我挑选了一张全班大合照，准备把它贴在成长纪念册的扉页作为最重要的开端。",
        "接着，我们开始在彩色卡纸上给未来的自己和最亲爱的师生写匿名赠言。",
        "王大壮写得抓耳挠腮，最后在给同桌的赠言里偷偷写了一句：“谢谢你借我三年的橡皮。”",
        "我把那封给未来的自己的长信折叠好，信中写满了对校园生活的感恩与眷恋。",
        "大家将所有的物件装进了一个厚实的金属罐子里，把它埋在操场的老枣树下。",
        "老师鼓励我们说，即便分别，这种真挚的情感表达也将跨越时空，成为永恒。",
        "阳光透过树叶散落在策划书上，分工明细一栏已经被汗水打湿了一角。",
        "当最后一勺土夯实，我知道，这段美好的小学生活已被完整地封锁在岁月的深处。",
        "我们相约十年后再来这里，通过这些文字与过去的青春重逢。"
      ],
      "vocabulary_used": [
        "活动策划书",
        "分工明细",
        "成长纪念册",
        "时间轴",
        "分类整理",
        "赠言",
        "成长素材",
        "感恩"
      ],
      "questions": [
        {
          "id": 1,
          "type": "true_false",
          "question": "文中提到的林悦在黑板上画时间轴是为了帮助大家理清成长的脉络。",
          "options": [],
          "answer": "对",
          "explanation": "文中第六句明确提到林悦画出时间轴带领大家搜集成长素材，这正是为了理清时间脉络。"
        },
        {
          "id": 2,
          "type": "choice",
          "question": "在这次活动中，王大壮在赠言中对同桌表达了什么？",
          "options": [
            "对他成绩的羡慕",
            "感谢他借了三年橡皮",
            "建议以后一起打球",
            "道歉弄坏了他的书本"
          ],
          "answer": "感谢他借了三年橡皮",
          "explanation": "根据文章第九句内容，王大壮在赠言里写了谢谢对方借了三年的橡皮。"
        },
        {
          "id": 3,
          "type": "fill_blank_text",
          "question": "林悦拿出的那份文件中，清晰地标注着什么？",
          "options": [],
          "answer": "分工明细",
          "explanation": "原文第二句提到“活动策划书，上面清晰地标注着分工明细”。"
        }
      ]
    },
    {
      "id": "chinese-g6down-s12",
      "unitNumber": 6,
      "unitTitle": "难忘小学生活",
      "storyIndex": 2,
      "title": "最后一次特别策划",
      "language": "Chinese",
      "sentences": [
        "距离毕业典礼只有三天了，晓峰和他的策划小组正在教室里热火朝天地讨论活动策划书。",
        "为了让这次聚会更有意义，晓峰建议采用栏目式的方法来梳理我们的六年时光。",
        "他在笔记本上列出了“初入校门”、“阳光运动”和“师恩难忘”三个大栏目。",
        "同学们纷纷贡献自己的资料搜集成果，从旧校徽到运动会的奖牌应有尽有。",
        "我们将这些宝贝进行分类整理，打算给每位老师都准备一份独特的成长纪念册。",
        "晓峰反复核对活动策划书里的时间地点，确保每个环节都不会出错。",
        "在准备礼物的过程中，最让大家纠结的是写给老师的赠言。",
        "“平时总觉得老师严厉，现在要落笔了，却发现满肚子的感激说不完。”晓峰感概万千。",
        "他提起笔，在一张精美的信纸上写下了对自己小学生活的真挚评价。",
        "这封书信不仅记录了课堂上的教诲，还回忆了生病时老师送来的那块热巧克力。",
        "每一份赠言都饱含着对师生的深情厚谊，是文字在毕业季绽放的花朵。",
        "到了典礼那天，当晓峰上台展示那份包含全班心血的栏目式画册时，台下响起了雷鸣般的掌声。",
        "老师们看着那些分类整理得整整齐齐的成长素材，眼里闪烁着感动的泪光。",
        "这场别开生面的告别盛宴，成为了我们小学生活最完美的句点。"
      ],
      "vocabulary_used": [
        "活动策划书",
        "栏目式",
        "资料搜集",
        "分类整理",
        "成长纪念册",
        "赠言",
        "书信",
        "成长素材"
      ],
      "questions": [
        {
          "id": 1,
          "type": "fill_blank_text",
          "question": "晓峰建议采用什么方法来梳理六年的时光？",
          "options": [],
          "answer": "栏目式",
          "explanation": "原文第二句提到“晓峰建议采用栏目式的方法来梳理我们的六年时光”。"
        },
        {
          "id": 2,
          "type": "choice",
          "question": "晓峰在给老师的书信中，回忆了哪件具体的温暖小事？",
          "options": [
            "老师带他去春游",
            "老师帮他辅导数学",
            "老师送的热巧克力",
            "老师带他参加比赛"
          ],
          "answer": "老师送的热巧克力",
          "explanation": "原文第十句写到信中回忆了生病时老师送来的那块热巧克力。"
        },
        {
          "id": 3,
          "type": "true_false",
          "question": "这篇文章主要讲述了同学们如何通过商业买卖的方式筹办毕业典礼。",
          "options": [],
          "answer": "错",
          "explanation": "文章讲述的是同学们利用所学知识，通过资料搜集、策划和手工制作纪念册来筹办充满情感的毕业活动，而非商业买卖。"
        }
      ]
    }
  ]
}